odoo/addons/account_cash_basis_group_base_line/README.rst
odoo/addons/account_cash_basis_group_base_line/__init__.py
odoo/addons/account_cash_basis_group_base_line/__manifest__.py
odoo/addons/account_cash_basis_group_base_line/i18n/account_cash_basis_group_base_line.pot
odoo/addons/account_cash_basis_group_base_line/models/__init__.py
odoo/addons/account_cash_basis_group_base_line/models/account_move.py
odoo/addons/account_cash_basis_group_base_line/readme/CONTRIBUTORS.rst
odoo/addons/account_cash_basis_group_base_line/readme/DESCRIPTION.rst
odoo/addons/account_cash_basis_group_base_line/readme/USAGE.rst
odoo/addons/account_cash_basis_group_base_line/static/description/icon.png
odoo/addons/account_cash_basis_group_base_line/static/description/index.html
odoo/addons/account_cash_basis_group_base_line/tests/__init__.py
odoo/addons/account_cash_basis_group_base_line/tests/test_reconciliation.py
odoo13_addon_account_cash_basis_group_base_line-13.0.0.0.2.dev4.dist-info/METADATA
odoo13_addon_account_cash_basis_group_base_line-13.0.0.0.2.dev4.dist-info/WHEEL
odoo13_addon_account_cash_basis_group_base_line-13.0.0.0.2.dev4.dist-info/top_level.txt
odoo13_addon_account_cash_basis_group_base_line-13.0.0.0.2.dev4.dist-info/RECORD
