Metadata-Version: 2.1
Name: odoo13-addon-account-cash-basis-group-base-line
Version: 13.0.0.0.2.dev4
Summary: Compacting the creation of Journal Lines for CABA base lines.
Home-page: https://github.com/OCA/account-financial-tools
Author: Vauxoo, Odoo Community Association (OCA)
Author-email: support@odoo-community.org
License: AGPL-3
Platform: UNKNOWN
Classifier: Programming Language :: Python
Classifier: Framework :: Odoo
Classifier: Framework :: Odoo :: 13.0
Classifier: License :: OSI Approved :: GNU Affero General Public License v3
Requires-Python: >=3.5
Requires-Dist: odoo <13.1dev,>=13.0a
